{"targets":[{"isStage":true,"name":"Stage","variables":{"=Wa={HPYEQm,6/~oB^h9":["Menu Flag","1"],"uzm+7ZecjQDnq3$XG$s/":["MenuSelection","0"],".v#L4N66Rb^[IHcNI2@K":["☁ InfDone",0,true],"MU2C1L@}Q}(^Efc:)C$H":["☁ redirect","90.html",true],"p%U,g:cj-*ZR61(^4]B}":["temp",60],"ZzkoA%G]o9|X9o-)W$i$":["☁ InfHP","0",true],"H$^*.cx%vxB9[$Qbs=Ty":["☁ InfWeaponsUnlocked","0",true],";#50Qx=y]f!eqK|]bDP,":["☁ InfAct",1,true],"NA]Z`_G?%Xj5$R6a*vk^":["act-temp","0"]},"lists":{":}LB~=1grhGm7IUX)EDw-Player Start Y-list":["Player Start Y",[-39,-69,-38,-66,-157,-23,-13,-31,-55,-116,-68,-6,65,-78,-20,7,-28,-129,-128,-37,-75,65,-120,-50,-81,69,-26,-76,-4,-125,136,23,-135,-83,1,-74,-110,-48,14,-112,-35,19,-138,-73,-73]],":}LB~=1grhGm7IUX)EDw-Player Start X-list":["Player Start X",[-205,-213,-211,-224,-222,-216,-205,-279,-213,-213,-211,-213,-209,-306,-217,-204,-205,-207,-210,-215,-209,-212,-212,-192,-215,-207,-211,-206,-216,-214,-142,-209,-223,-206,-213,-214,-204,-209,-213,-201,-212,-204,-218,-211,-221]],":}LB~=1grhGm7IUX)EDw-Projectile Y-list":["Projectile Y",[]],":}LB~=1grhGm7IUX)EDw-Projectile X-list":["Projectile X",[]],":}LB~=1grhGm7IUX)EDw-Projectile lifespan-list":["Projectile lifespan",[]],":}LB~=1grhGm7IUX)EDw-Only bad to enemies?-list":["Only bad to enemies?",[]],":}LB~=1grhGm7IUX)EDw-Projectile Xv-list":["Projectile Xv",[]],":}LB~=1grhGm7IUX)EDw-Projectile Yv-list":["Projectile Yv",[]],":}LB~=1grhGm7IUX)EDw-Projectile type-list":["Projectile type",[]],":}LB~=1grhGm7IUX)EDw-Direction-list":["Direction",[]],":}LB~=1grhGm7IUX)EDw-Costume #-list":["Costume #",[]],":}LB~=1grhGm7IUX)EDw-Size-list":["Size",[]],":}LB~=1grhGm7IUX)EDw-Size (for hurting)-list":["Size (for hurting)",["15","10","10","10","10","10","10","15","15","10","10","10","10","10","10","15","10","10","10","10","10","10","15","15","10","10","10","10","10","10","15","10","10","10","10","10","10","15","10","10","10","10","10","10","15","15","15","10","10","10","10","10","10","15","10","10","10","10","10","10","15","15","15","10","10","10","10","10","10","15","15","10","10","10","10","10","10","15","15","10","10","10","10","10","10","15","15","10","10","10","10","10","10","15","10","10","10","10","10","10","15","10","10","10","10","10","10","15","15","15","15","15","15","10","10","10","10","10","10","10","10","10","10","10","10","15","15","15","15","10","10","10","10","10","10","15","10","10","10","10","10","10","15","15","15","10","10","10","10","10","10","15","15","15","10","10","10","10","10","10","15","10","10","10","10","10","10","15","15","10","10","10","10","10","10","15","15","10","10","10","10","10","10","15","15","10","10","10","10","10","10","15","10","10","10","10","10","10","15","15","15","15","10","10","10","10","10","10","15","15","10","10","10","10","10","10","15","10","10","10","10","10","10","15","15","15","10","10","10","10","10","10","15","15","15","10","10","10","10","10","10","15","15"]]},"broadcasts":{"vSk-qw03`gDTJq-~bu+Z":"Cache All","X|pIX.xai(-z?A#=}e,4":"Darken"},"blocks":{",":{"opcode":"operator_equals","next":null,"parent":"y","inputs":{"OPERAND1":[3,"-",[10,""]],"OPERAND2":[1,[10,"1"]]},"fields":{},"shadow":false,"topLevel":false},"-":{"opcode":"sensing_of","next":null,"parent":",","inputs":{"OBJECT":[1,"a{"]},"fields":{"PROPERTY":["costume #",null]},"shadow":false,"topLevel":false},".":{"opcode":"control_forever","next":null,"parent":"z","inputs":{"SUBSTACK":[2,"/"]},"fields":{},"shadow":false,"topLevel":false},"/":{"opcode":"sound_playuntildone","next":null,"parent":".","inputs":{"SOUND_MENU":[1,"a|"]},"fields":{},"shadow":false,"topLevel":false},":":{"opcode":"operator_equals","next":null,"parent":"z","inputs":{"OPERAND1":[3,";",[10,""]],"OPERAND2":[1,[10,"2"]]},"fields":{},"shadow":false,"topLevel":false},";":{"opcode":"sensing_of","next":null,"parent":":","inputs":{"OBJECT":[1,"a}"]},"fields":{"PROPERTY":["costume #",null]},"shadow":false,"topLevel":false},"=":{"opcode":"sound_setvolumeto","next":"y","parent":"a~","inputs":{"VOLUME":[1,[4,"100"]]},"fields":{},"shadow":false,"topLevel":false},"?":{"opcode":"control_wait","next":"c","parent":"A","inputs":{"DURATION":[1,[5,"0"]]},"fields":{},"shadow":false,"topLevel":false},"a~":{"opcode":"event_whenflagclicked","next":"=","parent":null,"inputs":{},"fields":{},"shadow":false,"topLevel":true,"x":48,"y":64},"y":{"opcode":"control_wait_until","next":"z","parent":"=","inputs":{"CONDITION":[2,","]},"fields":{},"shadow":false,"topLevel":false},"a{":{"opcode":"sensing_of_object_menu","next":null,"parent":"-","inputs":{},"fields":{"OBJECT":["Main Menu",null]},"shadow":true,"topLevel":false},"z":{"opcode":"control_wait_until","next":".","parent":"y","inputs":{"CONDITION":[2,":"]},"fields":{},"shadow":false,"topLevel":false},"a}":{"opcode":"sensing_of_object_menu","next":null,"parent":";","inputs":{},"fields":{"OBJECT":["Main Menu",null]},"shadow":true,"topLevel":false},"a|":{"opcode":"sound_sounds_menu","next":null,"parent":"/","inputs":{},"fields":{"SOUND_MENU":["Pokémon Azalea Town - Qumu",null]},"shadow":true,"topLevel":false},"ba":{"opcode":"event_whenbroadcastreceived","next":"A","parent":null,"inputs":{},"fields":{"BROADCAST_OPTION":["Darken","X|pIX.xai(-z?A#=}e,4"]},"shadow":false,"topLevel":true,"x":621,"y":64},"bb":{"opcode":"sound_changevolumeby","next":null,"parent":"A","inputs":{"VOLUME":[1,[4,"-5"]]},"fields":{},"shadow":false,"topLevel":false},"A":{"opcode":"control_repeat","next":"?","parent":"ba","inputs":{"TIMES":[1,[6,"20"]],"SUBSTACK":[2,"bb"]},"fields":{},"shadow":false,"topLevel":false},"bc":{"opcode":"data_setvariableto","next":null,"parent":"c","inputs":{"VALUE":[1,[10,"931.html"]]},"fields":{"VARIABLE":["☁ redirect","MU2C1L@}Q}(^Efc:)C$H"]},"shadow":false,"topLevel":false},"c":{"opcode":"control_if_else","next":null,"parent":"?","inputs":{"CONDITION":[2,"bd"],"SUBSTACK":[2,"bc"],"SUBSTACK2":[2,"@"]},"fields":{},"shadow":false,"topLevel":false},"bd":{"opcode":"operator_equals","next":null,"parent":"c","inputs":{"OPERAND1":[3,[12,"act-temp","NA]Z`_G?%Xj5$R6a*vk^"],[10,""]],"OPERAND2":[1,[10,"3.5"]]},"fields":{},"shadow":false,"topLevel":false},"@":{"opcode":"data_setvariableto","next":null,"parent":"c","inputs":{"VALUE":[3,"[",[10,"0"]]},"fields":{"VARIABLE":["☁ redirect","MU2C1L@}Q}(^Efc:)C$H"]},"shadow":false,"topLevel":false},"[":{"opcode":"operator_join","next":null,"parent":"@","inputs":{"STRING1":[1,[10,"9"]],"STRING2":[3,"be",[10,"banana"]]},"fields":{},"shadow":false,"topLevel":false},"be":{"opcode":"operator_join","next":null,"parent":"[","inputs":{"STRING1":[3,[12,"act-temp","NA]Z`_G?%Xj5$R6a*vk^"],[10,"apple "]],"STRING2":[1,[10,".html"]]},"fields":{},"shadow":false,"topLevel":false}},"comments":{"cs":{"blockId":null,"x":159.62962962962962,"y":464.8148148148148,"width":350,"height":170,"minimized":false,"text":"Configuration for https://turbowarp.org/\nYou can move, resize, and minimize this comment, but don't edit it by hand. This comment can be deleted to remove the stored settings.\n{\"runtimeOptions\":{\"maxClones\":Infinity,\"miscLimits\":false,\"fencing\":false},\"width\":640} // _twconfig_"}},"currentCostume":0,"costumes":[{"assetId":"14e46ec3e2ba471c2adfe8f119052307","name":"","bitmapResolution":1,"md5ext":"14e46ec3e2ba471c2adfe8f119052307.svg","dataFormat":"svg","rotationCenterX":0,"rotationCenterY":0}],"sounds":[{"assetId":"92a48a2b3a7352588c38464a918c84ff","name":"Pokémon Azalea Town - Qumu","dataFormat":"wav","format":"","rate":48000,"sampleCount":9076958,"md5ext":"92a48a2b3a7352588c38464a918c84ff.wav"}],"volume":0,"layerOrder":0,"tempo":60,"videoTransparency":50,"videoState":"off","textToSpeechLanguage":"en"},{"isStage":false,"name":"Main Menu","variables":{"bohJIsLhCpZ;)4pO(kE`":["CloneID","3"],"*:$E$2ReHO~JTC;m1vW#":["CloneID2",10]},"lists":{},"broadcasts":{},"blocks":{"0":{"opcode":"control_wait_until","next":"a3","parent":"Z","inputs":{"CONDITION":[2,"b5"]},"fields":{},"shadow":false,"topLevel":false},"1":{"opcode":"control_repeat","next":"a4","parent":"a3","inputs":{"TIMES":[1,[6,"10"]],"SUBSTACK":[2,"b6"]},"fields":{},"shadow":false,"topLevel":false},"2":{"opcode":"control_if","next":null,"parent":"a6","inputs":{"CONDITION":[2,"b!"],"SUBSTACK":[2,"3"]},"fields":{},"shadow":false,"topLevel":false},"3":{"opcode":"control_repeat","next":"4","parent":"2","inputs":{"TIMES":[1,[6,"10"]],"SUBSTACK":[2,"b#"]},"fields":{},"shadow":false,"topLevel":false},"4":{"opcode":"sound_play","next":"b%","parent":"3","inputs":{"SOUND_MENU":[1,"b("]},"fields":{},"shadow":false,"topLevel":false},"5":{"opcode":"control_if","next":null,"parent":"m","inputs":{"CONDITION":[2,"cc"],"SUBSTACK":[2,"a-"]},"fields":{},"shadow":false,"topLevel":false},"6":{"opcode":"looks_switchcostumeto","next":"a%","parent":"a#","inputs":{"COSTUME":[1,"b-"]},"fields":{},"shadow":false,"topLevel":false},"7":{"opcode":"looks_setsizeto","next":"8","parent":"s","inputs":{"SIZE":[3,"a+",[4,"100"]]},"fields":{},"shadow":false,"topLevel":false},"8":{"opcode":"control_if","next":null,"parent":"7","inputs":{"CONDITION":[2,"b_"],"SUBSTACK":[2,"G"]},"fields":{},"shadow":false,"topLevel":false},"9":{"opcode":"looks_switchcostumeto","next":"a.","parent":"a-","inputs":{"COSTUME":[1,"cd"]},"fields":{},"shadow":false,"topLevel":false},"B":{"opcode":"looks_seteffectto","next":"]","parent":"C","inputs":{"VALUE":[3,"^",[4,"0"]]},"fields":{"EFFECT":["BRIGHTNESS",null]},"shadow":false,"topLevel":false},"D":{"opcode":"control_wait_until","next":"E","parent":"]","inputs":{"CONDITION":[2,"bf"]},"fields":{},"shadow":false,"topLevel":false},"E":{"opcode":"control_repeat","next":"_","parent":"D","inputs":{"TIMES":[1,[6,"10"]],"SUBSTACK":[2,"bg"]},"fields":{},"shadow":false,"topLevel":false},"F":{"opcode":"sound_playuntildone","next":"a","parent":"G","inputs":{"SOUND_MENU":[1,"bh"]},"fields":{},"shadow":false,"topLevel":false},"H":{"opcode":"control_if_else","next":null,"parent":"a","inputs":{"CONDITION":[2,"bi"],"SUBSTACK":[2,"bj"]},"fields":{},"shadow":false,"topLevel":false},"bk":{"opcode":"event_whenflagclicked","next":"`","parent":null,"inputs":{},"fields":{},"shadow":false,"topLevel":true,"x":48,"y":64},"`":{"opcode":"looks_cleargraphiceffects","next":"b","parent":"bk","inputs":{},"fields":{},"shadow":false,"topLevel":false},"b":{"opcode":"control_if_else","next":"d","parent":"`","inputs":{"CONDITION":[2,"I"],"SUBSTACK":[2,"{"],"SUBSTACK2":[2,"bl"]},"fields":{},"shadow":false,"topLevel":false},"I":{"opcode":"operator_or","next":null,"parent":"b","inputs":{"OPERAND1":[2,"bm"],"OPERAND2":[2,"bn"]},"fields":{},"shadow":false,"topLevel":false},"bm":{"opcode":"operator_equals","next":null,"parent":"I","inputs":{"OPERAND1":[3,[12,"☁ InfAct",";#50Qx=y]f!eqK|]bDP,"],[10,""]],"OPERAND2":[1,[10,"0"]]},"fields":{},"shadow":false,"topLevel":false},"bn":{"opcode":"operator_gt","next":null,"parent":"I","inputs":{"OPERAND1":[3,[12,"☁ InfAct",";#50Qx=y]f!eqK|]bDP,"],[10,""]],"OPERAND2":[1,[10,"6"]]},"fields":{},"shadow":false,"topLevel":false},"{":{"opcode":"data_setvariableto","next":"bo","parent":"b","inputs":{"VALUE":[1,[10,"1"]]},"fields":{"VARIABLE":["☁ InfAct",";#50Qx=y]f!eqK|]bDP,"]},"shadow":false,"topLevel":false},"bo":{"opcode":"data_setvariableto","next":null,"parent":"{","inputs":{"VALUE":[1,[10,"1"]]},"fields":{"VARIABLE":["act-temp","NA]Z`_G?%Xj5$R6a*vk^"]},"shadow":false,"topLevel":false},"bl":{"opcode":"data_setvariableto","next":null,"parent":"b","inputs":{"VALUE":[3,[12,"☁ InfAct",";#50Qx=y]f!eqK|]bDP,"],[10,"1"]]},"fields":{"VARIABLE":["act-temp","NA]Z`_G?%Xj5$R6a*vk^"]},"shadow":false,"topLevel":false},"d":{"opcode":"control_if","next":"|","parent":"b","inputs":{"CONDITION":[2,"bp"],"SUBSTACK":[2,"bq"]},"fields":{},"shadow":false,"topLevel":false},"bp":{"opcode":"operator_equals","next":null,"parent":"d","inputs":{"OPERAND1":[3,[12,"☁ InfDone",".v#L4N66Rb^[IHcNI2@K"],[10,""]],"OPERAND2":[1,[10,"1"]]},"fields":{},"shadow":false,"topLevel":false},"bq":{"opcode":"data_setvariableto","next":null,"parent":"d","inputs":{"VALUE":[1,[10,"7"]]},"fields":{"VARIABLE":["☁ InfAct",";#50Qx=y]f!eqK|]bDP,"]},"shadow":false,"topLevel":false},"|":{"opcode":"looks_gotofrontback","next":"}","parent":"d","inputs":{},"fields":{"FRONT_BACK":["front",null]},"shadow":false,"topLevel":false},"}":{"opcode":"looks_setsizeto","next":"~","parent":"|","inputs":{"SIZE":[1,[4,"100"]]},"fields":{},"shadow":false,"topLevel":false},"~":{"opcode":"looks_show","next":"aa","parent":"}","inputs":{},"fields":{},"shadow":false,"topLevel":false},"aa":{"opcode":"motion_gotoxy","next":"ab","parent":"~","inputs":{"X":[1,[4,"0"]],"Y":[1,[4,"0"]]},"fields":{},"shadow":false,"topLevel":false},"ab":{"opcode":"looks_seteffectto","next":"J","parent":"aa","inputs":{"VALUE":[1,[4,"-100"]]},"fields":{"EFFECT":["BRIGHTNESS",null]},"shadow":false,"topLevel":false},"J":{"opcode":"looks_switchcostumeto","next":"K","parent":"ab","inputs":{"COSTUME":[1,"br"]},"fields":{},"shadow":false,"topLevel":false},"br":{"opcode":"looks_costume","next":null,"parent":"J","inputs":{},"fields":{"COSTUME":["Caution",null]},"shadow":true,"topLevel":false},"K":{"opcode":"control_repeat","next":"ac","parent":"J","inputs":{"TIMES":[1,[6,"20"]],"SUBSTACK":[2,"bs"]},"fields":{},"shadow":false,"topLevel":false},"bs":{"opcode":"looks_changeeffectby","next":null,"parent":"K","inputs":{"CHANGE":[1,[4,"5"]]},"fields":{"EFFECT":["BRIGHTNESS",null]},"shadow":false,"topLevel":false},"ac":{"opcode":"event_broadcastandwait","next":"L","parent":"K","inputs":{"BROADCAST_INPUT":[1,[11,"Cache All","vSk-qw03`gDTJq-~bu+Z"]]},"fields":{},"shadow":false,"topLevel":false},"L":{"opcode":"control_wait_until","next":"M","parent":"ac","inputs":{"CONDITION":[2,"bt"]},"fields":{},"shadow":false,"topLevel":false},"bt":{"opcode":"sensing_mousedown","next":null,"parent":"L","inputs":{},"fields":{},"shadow":false,"topLevel":false},"M":{"opcode":"control_repeat","next":"N","parent":"L","inputs":{"TIMES":[1,[6,"20"]],"SUBSTACK":[2,"bu"]},"fields":{},"shadow":false,"topLevel":false},"bu":{"opcode":"looks_changeeffectby","next":null,"parent":"M","inputs":{"CHANGE":[1,[4,"-5"]]},"fields":{"EFFECT":["BRIGHTNESS",null]},"shadow":false,"topLevel":false},"N":{"opcode":"looks_switchcostumeto","next":"O","parent":"M","inputs":{"COSTUME":[1,"bv"]},"fields":{},"shadow":false,"topLevel":false},"bv":{"opcode":"looks_costume","next":null,"parent":"N","inputs":{},"fields":{"COSTUME":["BG",null]},"shadow":true,"topLevel":false},"O":{"opcode":"control_repeat","next":"ad","parent":"N","inputs":{"TIMES":[1,[6,"20"]],"SUBSTACK":[2,"bw"]},"fields":{},"shadow":false,"topLevel":false},"bw":{"opcode":"looks_changeeffectby","next":null,"parent":"O","inputs":{"CHANGE":[1,[4,"5"]]},"fields":{"EFFECT":["BRIGHTNESS",null]},"shadow":false,"topLevel":false},"ad":{"opcode":"looks_cleargraphiceffects","next":"ae","parent":"O","inputs":{},"fields":{},"shadow":false,"topLevel":false},"ae":{"opcode":"procedures_call","next":"af","parent":"ad","inputs":{},"fields":{},"shadow":false,"topLevel":false,"mutation":{"tagName":"mutation","children":[],"proccode":"Logo Starter","argumentids":"[]","warp":"true"}},"af":{"opcode":"procedures_call","next":"ag","parent":"ae","inputs":{},"fields":{},"shadow":false,"topLevel":false,"mutation":{"tagName":"mutation","children":[],"proccode":"Button Maker","argumentids":"[]","warp":"true"}},"ag":{"opcode":"control_wait","next":"bx","parent":"af","inputs":{"DURATION":[1,[5,"1"]]},"fields":{},"shadow":false,"topLevel":false},"bx":{"opcode":"data_setvariableto","next":null,"parent":"ag","inputs":{"VALUE":[1,[10,"1"]]},"fields":{"VARIABLE":["Menu Flag","=Wa={HPYEQm,6/~oB^h9"]},"shadow":false,"topLevel":false},"ah":{"opcode":"procedures_definition","next":"ai","parent":null,"inputs":{"custom_block":[1,"by"]},"fields":{},"shadow":false,"topLevel":true,"x":1315,"y":64},"by":{"opcode":"procedures_prototype","next":null,"parent":"ah","inputs":{},"fields":{},"shadow":true,"topLevel":false,"mutation":{"tagName":"mutation","children":[],"proccode":"Logo Starter","argumentids":"[]","argumentnames":"[]","argumentdefaults":"[]","warp":"true"}},"ai":{"opcode":"data_setvariableto","next":"aj","parent":"ah","inputs":{"VALUE":[1,[10,"0"]]},"fields":{"VARIABLE":["Menu Flag","=Wa={HPYEQm,6/~oB^h9"]},"shadow":false,"topLevel":false},"aj":{"opcode":"data_setvariableto","next":"ak","parent":"ai","inputs":{"VALUE":[1,[10,"0"]]},"fields":{"VARIABLE":["CloneID","bohJIsLhCpZ;)4pO(kE`"]},"shadow":false,"topLevel":false},"ak":{"opcode":"data_setvariableto","next":"P","parent":"aj","inputs":{"VALUE":[1,[10,"0"]]},"fields":{"VARIABLE":["CloneID2","*:$E$2ReHO~JTC;m1vW#"]},"shadow":false,"topLevel":false},"P":{"opcode":"data_setvariableto","next":"al","parent":"ak","inputs":{"VALUE":[3,"Q",[10,"0"]]},"fields":{"VARIABLE":["temp","p%U,g:cj-*ZR61(^4]B}"]},"shadow":false,"topLevel":false},"Q":{"opcode":"operator_random","next":null,"parent":"P","inputs":{"FROM":[3,"bz",[4,"1"]],"TO":[3,"bA",[4,"50"]]},"fields":{},"shadow":false,"topLevel":false},"bz":{"opcode":"operator_random","next":null,"parent":"Q","inputs":{"FROM":[1,[4,"1"]],"TO":[1,[4,"50"]]},"fields":{},"shadow":false,"topLevel":false},"bA":{"opcode":"operator_random","next":null,"parent":"Q","inputs":{"FROM":[1,[4,"25"]],"TO":[1,[4,"100"]]},"fields":{},"shadow":false,"topLevel":false},"al":{"opcode":"control_repeat","next":null,"parent":"P","inputs":{"TIMES":[1,[6,"40"]],"SUBSTACK":[2,"am"]},"fields":{},"shadow":false,"topLevel":false},"am":{"opcode":"data_changevariableby","next":"an","parent":"al","inputs":{"VALUE":[1,[4,"1"]]},"fields":{"VARIABLE":["CloneID2","*:$E$2ReHO~JTC;m1vW#"]},"shadow":false,"topLevel":false},"an":{"opcode":"control_create_clone_of","next":null,"parent":"am","inputs":{"CLONE_OPTION":[1,"bB"]},"fields":{},"shadow":false,"topLevel":false},"bB":{"opcode":"control_create_clone_of_menu","next":null,"parent":"an","inputs":{},"fields":{"CLONE_OPTION":["_myself_",null]},"shadow":true,"topLevel":false},"ao":{"opcode":"procedures_definition","next":"ap","parent":null,"inputs":{"custom_block":[1,"bC"]},"fields":{},"shadow":false,"topLevel":true,"x":1315,"y":584},"bC":{"opcode":"procedures_prototype","next":null,"parent":"ao","inputs":{},"fields":{},"shadow":true,"topLevel":false,"mutation":{"tagName":"mutation","children":[],"proccode":"Button Maker","argumentids":"[]","argumentnames":"[]","argumentdefaults":"[]","warp":"true"}},"ap":{"opcode":"data_setvariableto","next":"aq","parent":"ao","inputs":{"VALUE":[1,[10,"1"]]},"fields":{"VARIABLE":["CloneID","bohJIsLhCpZ;)4pO(kE`"]},"shadow":false,"topLevel":false},"aq":{"opcode":"data_setvariableto","next":"R","parent":"ap","inputs":{"VALUE":[1,[10,"0"]]},"fields":{"VARIABLE":["CloneID2","*:$E$2ReHO~JTC;m1vW#"]},"shadow":false,"topLevel":false},"R":{"opcode":"control_repeat","next":"e","parent":"aq","inputs":{"TIMES":[1,[6,"10"]],"SUBSTACK":[2,"ar"]},"fields":{},"shadow":false,"topLevel":false},"ar":{"opcode":"data_changevariableby","next":"as","parent":"R","inputs":{"VALUE":[1,[4,"1"]]},"fields":{"VARIABLE":["CloneID2","*:$E$2ReHO~JTC;m1vW#"]},"shadow":false,"topLevel":false},"as":{"opcode":"control_create_clone_of","next":null,"parent":"ar","inputs":{"CLONE_OPTION":[1,"bD"]},"fields":{},"shadow":false,"topLevel":false},"bD":{"opcode":"control_create_clone_of_menu","next":null,"parent":"as","inputs":{},"fields":{"CLONE_OPTION":["_myself_",null]},"shadow":true,"topLevel":false},"e":{"opcode":"control_if","next":"at","parent":"R","inputs":{"CONDITION":[2,"bE"],"SUBSTACK":[2,"au"]},"fields":{},"shadow":false,"topLevel":false},"bE":{"opcode":"operator_gt","next":null,"parent":"e","inputs":{"OPERAND1":[3,[12,"☁ InfAct",";#50Qx=y]f!eqK|]bDP,"],[10,""]],"OPERAND2":[1,[10,"1"]]},"fields":{},"shadow":false,"topLevel":false},"au":{"opcode":"data_setvariableto","next":"av","parent":"e","inputs":{"VALUE":[1,[10,"2"]]},"fields":{"VARIABLE":["CloneID","bohJIsLhCpZ;)4pO(kE`"]},"shadow":false,"topLevel":false},"av":{"opcode":"data_setvariableto","next":"aw","parent":"au","inputs":{"VALUE":[1,[10,"0"]]},"fields":{"VARIABLE":["CloneID2","*:$E$2ReHO~JTC;m1vW#"]},"shadow":false,"topLevel":false},"aw":{"opcode":"control_repeat","next":null,"parent":"av","inputs":{"TIMES":[1,[6,"10"]],"SUBSTACK":[2,"ax"]},"fields":{},"shadow":false,"topLevel":false},"ax":{"opcode":"data_changevariableby","next":"ay","parent":"aw","inputs":{"VALUE":[1,[4,"1"]]},"fields":{"VARIABLE":["CloneID2","*:$E$2ReHO~JTC;m1vW#"]},"shadow":false,"topLevel":false},"ay":{"opcode":"control_create_clone_of","next":null,"parent":"ax","inputs":{"CLONE_OPTION":[1,"bF"]},"fields":{},"shadow":false,"topLevel":false},"bF":{"opcode":"control_create_clone_of_menu","next":null,"parent":"ay","inputs":{},"fields":{"CLONE_OPTION":["_myself_",null]},"shadow":true,"topLevel":false},"az":{"opcode":"control_repeat","next":null,"parent":"aA","inputs":{"TIMES":[1,[6,"10"]],"SUBSTACK":[2,"aB"]},"fields":{},"shadow":false,"topLevel":false},"aB":{"opcode":"data_changevariableby","next":"aC","parent":"az","inputs":{"VALUE":[1,[4,"1"]]},"fields":{"VARIABLE":["CloneID2","*:$E$2ReHO~JTC;m1vW#"]},"shadow":false,"topLevel":false},"aC":{"opcode":"control_create_clone_of","next":null,"parent":"aB","inputs":{"CLONE_OPTION":[1,"bG"]},"fields":{},"shadow":false,"topLevel":false},"bG":{"opcode":"control_create_clone_of_menu","next":null,"parent":"aC","inputs":{},"fields":{"CLONE_OPTION":["_myself_",null]},"shadow":true,"topLevel":false},"bH":{"opcode":"event_whenbroadcastreceived","next":"aD","parent":null,"inputs":{},"fields":{"BROADCAST_OPTION":["Darken","X|pIX.xai(-z?A#=}e,4"]},"shadow":false,"topLevel":true,"x":1315,"y":1632},"aD":{"opcode":"control_repeat","next":null,"parent":"bH","inputs":{"TIMES":[1,[6,"20"]],"SUBSTACK":[2,"bI"]},"fields":{},"shadow":false,"topLevel":false},"bI":{"opcode":"looks_changeeffectby","next":null,"parent":"aD","inputs":{"CHANGE":[1,[4,"-5"]]},"fields":{"EFFECT":["BRIGHTNESS",null]},"shadow":false,"topLevel":false},"bJ":{"opcode":"control_start_as_clone","next":"f","parent":null,"inputs":{},"fields":{},"shadow":false,"topLevel":true,"x":671,"y":64},"f":{"opcode":"control_if","next":"g","parent":"bJ","inputs":{"CONDITION":[2,"bK"],"SUBSTACK":[2,"S"]},"fields":{},"shadow":false,"topLevel":false},"bK":{"opcode":"operator_equals","next":null,"parent":"f","inputs":{"OPERAND1":[3,[12,"CloneID","bohJIsLhCpZ;)4pO(kE`"],[10,""]],"OPERAND2":[1,[10,"0"]]},"fields":{},"shadow":false,"topLevel":false},"S":{"opcode":"looks_switchcostumeto","next":"aE","parent":"f","inputs":{"COSTUME":[1,"bL"]},"fields":{},"shadow":false,"topLevel":false},"bL":{"opcode":"looks_costume","next":null,"parent":"S","inputs":{},"fields":{"COSTUME":["Title",null]},"shadow":true,"topLevel":false},"aE":{"opcode":"looks_gotofrontback","next":"T","parent":"S","inputs":{},"fields":{"FRONT_BACK":["front",null]},"shadow":false,"topLevel":false},"T":{"opcode":"motion_gotoxy","next":"U","parent":"aE","inputs":{"X":[3,"aF",[4,"-732"]],"Y":[1,[4,"80"]]},"fields":{},"shadow":false,"topLevel":false},"aF":{"opcode":"operator_add","next":null,"parent":"T","inputs":{"NUM1":[1,[4,"-732"]],"NUM2":[3,"bM",[4,""]]},"fields":{},"shadow":false,"topLevel":false},"bM":{"opcode":"operator_multiply","next":null,"parent":"aF","inputs":{"NUM1":[3,[12,"CloneID2","*:$E$2ReHO~JTC;m1vW#"],[4,""]],"NUM2":[1,[4,"1.25"]]},"fields":{},"shadow":false,"topLevel":false},"U":{"opcode":"looks_setsizeto","next":"h","parent":"T","inputs":{"SIZE":[3,"aG",[4,"100"]]},"fields":{},"shadow":false,"topLevel":false},"aG":{"opcode":"operator_add","next":null,"parent":"U","inputs":{"NUM1":[3,"bN",[4,""]],"NUM2":[1,[4,"96"]]},"fields":{},"shadow":false,"topLevel":false},"bN":{"opcode":"operator_multiply","next":null,"parent":"aG","inputs":{"NUM1":[3,[12,"CloneID2","*:$E$2ReHO~JTC;m1vW#"],[4,""]],"NUM2":[1,[4,"0.15"]]},"fields":{},"shadow":false,"topLevel":false},"h":{"opcode":"control_if","next":"i","parent":"U","inputs":{"CONDITION":[2,"aH"],"SUBSTACK":[2,"aI"]},"fields":{},"shadow":false,"topLevel":false},"aH":{"opcode":"operator_not","next":null,"parent":"h","inputs":{"OPERAND":[2,"bO"]},"fields":{},"shadow":false,"topLevel":false},"bO":{"opcode":"operator_equals","next":null,"parent":"aH","inputs":{"OPERAND1":[3,[12,"CloneID2","*:$E$2ReHO~JTC;m1vW#"],[10,""]],"OPERAND2":[1,[10,"40"]]},"fields":{},"shadow":false,"topLevel":false},"aI":{"opcode":"looks_seteffectto","next":null,"parent":"h","inputs":{"VALUE":[3,"aJ",[4,"0"]]},"fields":{"EFFECT":["BRIGHTNESS",null]},"shadow":false,"topLevel":false},"aJ":{"opcode":"operator_add","next":null,"parent":"aI","inputs":{"NUM1":[1,[4,"-100"]],"NUM2":[3,"bP",[4,""]]},"fields":{},"shadow":false,"topLevel":false},"bP":{"opcode":"operator_multiply","next":null,"parent":"aJ","inputs":{"NUM1":[3,[12,"CloneID2","*:$E$2ReHO~JTC;m1vW#"],[4,""]],"NUM2":[1,[4,"2"]]},"fields":{},"shadow":false,"topLevel":false},"i":{"opcode":"control_if","next":"j","parent":"h","inputs":{"CONDITION":[2,"bQ"],"SUBSTACK":[2,"aK"]},"fields":{},"shadow":false,"topLevel":false},"bQ":{"opcode":"operator_equals","next":null,"parent":"i","inputs":{"OPERAND1":[3,[12,"temp","p%U,g:cj-*ZR61(^4]B}"],[10,""]],"OPERAND2":[1,[10,"80"]]},"fields":{},"shadow":false,"topLevel":false},"aK":{"opcode":"looks_seteffectto","next":null,"parent":"i","inputs":{"VALUE":[3,"aL",[4,"0"]]},"fields":{"EFFECT":["WHIRL",null]},"shadow":false,"topLevel":false},"aL":{"opcode":"operator_subtract","next":null,"parent":"aK","inputs":{"NUM1":[1,[4,"60"]],"NUM2":[3,"bR",[4,""]]},"fields":{},"shadow":false,"topLevel":false},"bR":{"opcode":"operator_multiply","next":null,"parent":"aL","inputs":{"NUM1":[3,[12,"CloneID2","*:$E$2ReHO~JTC;m1vW#"],[4,""]],"NUM2":[1,[4,"3"]]},"fields":{},"shadow":false,"topLevel":false},"j":{"opcode":"control_if","next":"k","parent":"i","inputs":{"CONDITION":[2,"bS"],"SUBSTACK":[2,"aM"]},"fields":{},"shadow":false,"topLevel":false},"bS":{"opcode":"operator_equals","next":null,"parent":"j","inputs":{"OPERAND1":[3,[12,"temp","p%U,g:cj-*ZR61(^4]B}"],[10,""]],"OPERAND2":[1,[10,"40"]]},"fields":{},"shadow":false,"topLevel":false},"aM":{"opcode":"looks_seteffectto","next":"bT","parent":"j","inputs":{"VALUE":[1,[4,"0"]]},"fields":{"EFFECT":["WHIRL",null]},"shadow":false,"topLevel":false},"bT":{"opcode":"looks_seteffectto","next":null,"parent":"aM","inputs":{"VALUE":[1,[4,"5"]]},"fields":{"EFFECT":["MOSAIC",null]},"shadow":false,"topLevel":false},"k":{"opcode":"control_if","next":"l","parent":"j","inputs":{"CONDITION":[2,"bU"],"SUBSTACK":[2,"aN"]},"fields":{},"shadow":false,"topLevel":false},"bU":{"opcode":"operator_equals","next":null,"parent":"k","inputs":{"OPERAND1":[3,[12,"temp","p%U,g:cj-*ZR61(^4]B}"],[10,""]],"OPERAND2":[1,[10,"60"]]},"fields":{},"shadow":false,"topLevel":false},"aN":{"opcode":"looks_seteffectto","next":"aO","parent":"k","inputs":{"VALUE":[1,[4,"0"]]},"fields":{"EFFECT":["WHIRL",null]},"shadow":false,"topLevel":false},"aO":{"opcode":"looks_seteffectto","next":"aP","parent":"aN","inputs":{"VALUE":[1,[4,"0"]]},"fields":{"EFFECT":["MOSAIC",null]},"shadow":false,"topLevel":false},"aP":{"opcode":"looks_seteffectto","next":null,"parent":"aO","inputs":{"VALUE":[3,"aQ",[4,"0"]]},"fields":{"EFFECT":["COLOR",null]},"shadow":false,"topLevel":false},"aQ":{"opcode":"operator_subtract","next":null,"parent":"aP","inputs":{"NUM1":[1,[4,"70"]],"NUM2":[3,"bV",[4,""]]},"fields":{},"shadow":false,"topLevel":false},"bV":{"opcode":"operator_multiply","next":null,"parent":"aQ","inputs":{"NUM1":[3,[12,"CloneID2","*:$E$2ReHO~JTC;m1vW#"],[4,""]],"NUM2":[1,[4,"2"]]},"fields":{},"shadow":false,"topLevel":false},"l":{"opcode":"control_repeat_until","next":"aR","parent":"k","inputs":{"CONDITION":[2,"aS"],"SUBSTACK":[2,"aT"]},"fields":{},"shadow":false,"topLevel":false},"aS":{"opcode":"operator_lt","next":null,"parent":"l","inputs":{"OPERAND1":[3,"aU",[10,""]],"OPERAND2":[1,[10,"1"]]},"fields":{},"shadow":false,"topLevel":false},"aU":{"opcode":"operator_mathop","next":null,"parent":"aS","inputs":{"NUM":[3,"bW",[4,""]]},"fields":{"OPERATOR":["abs",null]},"shadow":false,"topLevel":false},"bW":{"opcode":"motion_xposition","next":null,"parent":"aU","inputs":{},"fields":{},"shadow":false,"topLevel":false},"aT":{"opcode":"motion_gotoxy","next":null,"parent":"l","inputs":{"X":[3,"aV",[4,"0"]],"Y":[1,[4,"80"]]},"fields":{},"shadow":false,"topLevel":false},"aV":{"opcode":"operator_divide","next":null,"parent":"aT","inputs":{"NUM1":[3,"bX",[4,""]],"NUM2":[1,[4,"2"]]},"fields":{},"shadow":false,"topLevel":false},"bX":{"opcode":"motion_xposition","next":null,"parent":"aV","inputs":{},"fields":{},"shadow":false,"topLevel":false},"aR":{"opcode":"motion_gotoxy","next":"V","parent":"l","inputs":{"X":[1,[4,"0"]],"Y":[1,[4,"80"]]},"fields":{},"shadow":false,"topLevel":false},"V":{"opcode":"control_wait_until","next":"aW","parent":"aR","inputs":{"CONDITION":[2,"bY"]},"fields":{},"shadow":false,"topLevel":false},"bY":{"opcode":"operator_equals","next":null,"parent":"V","inputs":{"OPERAND1":[3,[12,"Menu Flag","=Wa={HPYEQm,6/~oB^h9"],[10,""]],"OPERAND2":[1,[10,"1"]]},"fields":{},"shadow":false,"topLevel":false},"aW":{"opcode":"motion_pointindirection","next":"aX","parent":"V","inputs":{"DIRECTION":[1,[8,"90"]]},"fields":{},"shadow":false,"topLevel":false},"aX":{"opcode":"control_forever","next":null,"parent":"aW","inputs":{"SUBSTACK":[2,"W"]},"fields":{},"shadow":false,"topLevel":false},"W":{"opcode":"control_repeat","next":"aY","parent":"aX","inputs":{"TIMES":[1,[6,"20"]],"SUBSTACK":[2,"bZ"]},"fields":{},"shadow":false,"topLevel":false},"bZ":{"opcode":"looks_changesizeby","next":null,"parent":"W","inputs":{"CHANGE":[1,[4,"0.25"]]},"fields":{},"shadow":false,"topLevel":false},"aY":{"opcode":"control_repeat","next":null,"parent":"W","inputs":{"TIMES":[1,[6,"20"]],"SUBSTACK":[2,"b0"]},"fields":{},"shadow":false,"topLevel":false},"b0":{"opcode":"looks_changesizeby","next":null,"parent":"aY","inputs":{"CHANGE":[1,[4,"-0.25"]]},"fields":{},"shadow":false,"topLevel":false},"g":{"opcode":"control_if","next":"m","parent":"f","inputs":{"CONDITION":[2,"b1"],"SUBSTACK":[2,"aZ"]},"fields":{},"shadow":false,"topLevel":false},"b1":{"opcode":"operator_equals","next":null,"parent":"g","inputs":{"OPERAND1":[3,[12,"CloneID","bohJIsLhCpZ;)4pO(kE`"],[10,""]],"OPERAND2":[1,[10,"1"]]},"fields":{},"shadow":false,"topLevel":false},"aZ":{"opcode":"looks_seteffectto","next":"X","parent":"g","inputs":{"VALUE":[1,[4,"100"]]},"fields":{"EFFECT":["GHOST",null]},"shadow":false,"topLevel":false},"X":{"opcode":"looks_switchcostumeto","next":"a0","parent":"aZ","inputs":{"COSTUME":[1,"b2"]},"fields":{},"shadow":false,"topLevel":false},"b2":{"opcode":"looks_costume","next":null,"parent":"X","inputs":{},"fields":{"COSTUME":["costume1",null]},"shadow":true,"topLevel":false},"a0":{"opcode":"looks_gotofrontback","next":"Y","parent":"X","inputs":{},"fields":{"FRONT_BACK":["front",null]},"shadow":false,"topLevel":false},"Y":{"opcode":"looks_setsizeto","next":"Z","parent":"a0","inputs":{"SIZE":[3,"a1",[4,"100"]]},"fields":{},"shadow":false,"topLevel":false},"a1":{"opcode":"operator_add","next":null,"parent":"Y","inputs":{"NUM1":[3,"b3",[4,""]],"NUM2":[1,[4,"95"]]},"fields":{},"shadow":false,"topLevel":false},"b3":{"opcode":"operator_multiply","next":null,"parent":"a1","inputs":{"NUM1":[3,[12,"CloneID2","*:$E$2ReHO~JTC;m1vW#"],[4,""]],"NUM2":[1,[4,"0.5"]]},"fields":{},"shadow":false,"topLevel":false},"Z":{"opcode":"looks_seteffectto","next":"0","parent":"Y","inputs":{"VALUE":[3,"a2",[4,"0"]]},"fields":{"EFFECT":["BRIGHTNESS",null]},"shadow":false,"topLevel":false},"a2":{"opcode":"operator_add","next":null,"parent":"Z","inputs":{"NUM1":[1,[4,"-20"]],"NUM2":[3,"b4",[4,""]]},"fields":{},"shadow":false,"topLevel":false},"b4":{"opcode":"operator_multiply","next":null,"parent":"a2","inputs":{"NUM1":[3,[12,"CloneID2","*:$E$2ReHO~JTC;m1vW#"],[4,""]],"NUM2":[1,[4,"2"]]},"fields":{},"shadow":false,"topLevel":false},"b5":{"opcode":"operator_equals","next":null,"parent":"0","inputs":{"OPERAND1":[3,[12,"Menu Flag","=Wa={HPYEQm,6/~oB^h9"],[10,""]],"OPERAND2":[1,[10,"1"]]},"fields":{},"shadow":false,"topLevel":false},"a3":{"opcode":"motion_gotoxy","next":"1","parent":"0","inputs":{"X":[1,[4,"-100"]],"Y":[1,[4,"-50"]]},"fields":{},"shadow":false,"topLevel":false},"b6":{"opcode":"looks_changeeffectby","next":null,"parent":"1","inputs":{"CHANGE":[1,[4,"-10"]]},"fields":{"EFFECT":["GHOST",null]},"shadow":false,"topLevel":false},"a4":{"opcode":"control_forever","next":null,"parent":"1","inputs":{"SUBSTACK":[2,"n"]},"fields":{},"shadow":false,"topLevel":false},"n":{"opcode":"control_if","next":"o","parent":"a4","inputs":{"CONDITION":[2,"b7"],"SUBSTACK":[2,"p"]},"fields":{},"shadow":false,"topLevel":false},"b7":{"opcode":"operator_equals","next":null,"parent":"n","inputs":{"OPERAND1":[3,[12,"CloneID2","*:$E$2ReHO~JTC;m1vW#"],[10,""]],"OPERAND2":[1,[10,"1"]]},"fields":{},"shadow":false,"topLevel":false},"p":{"opcode":"control_if_else","next":null,"parent":"n","inputs":{"CONDITION":[2,"a5"],"SUBSTACK":[2,"a6"],"SUBSTACK2":[2,"b8"]},"fields":{},"shadow":false,"topLevel":false},"a5":{"opcode":"sensing_touchingobject","next":null,"parent":"p","inputs":{"TOUCHINGOBJECTMENU":[1,"b9"]},"fields":{},"shadow":false,"topLevel":false},"b9":{"opcode":"sensing_touchingobjectmenu","next":null,"parent":"a5","inputs":{},"fields":{"TOUCHINGOBJECTMENU":["_mouse_",null]},"shadow":true,"topLevel":false},"a6":{"opcode":"data_setvariableto","next":"2","parent":"p","inputs":{"VALUE":[1,[10,"1"]]},"fields":{"VARIABLE":["MenuSelection","uzm+7ZecjQDnq3$XG$s/"]},"shadow":false,"topLevel":false},"b!":{"opcode":"sensing_mousedown","next":null,"parent":"2","inputs":{},"fields":{},"shadow":false,"topLevel":false},"b#":{"opcode":"looks_changeeffectby","next":null,"parent":"3","inputs":{"CHANGE":[1,[4,"10"]]},"fields":{"EFFECT":["GHOST",null]},"shadow":false,"topLevel":false},"b(":{"opcode":"sound_sounds_menu","next":null,"parent":"4","inputs":{},"fields":{"SOUND_MENU":["mixkit-arcade-game-jump-coin-216",null]},"shadow":true,"topLevel":false},"b%":{"opcode":"event_broadcastandwait","next":null,"parent":"4","inputs":{"BROADCAST_INPUT":[1,[11,"Darken","X|pIX.xai(-z?A#=}e,4"]]},"fields":{},"shadow":false,"topLevel":false},"b8":{"opcode":"data_setvariableto","next":null,"parent":"p","inputs":{"VALUE":[1,[10,"0"]]},"fields":{"VARIABLE":["MenuSelection","uzm+7ZecjQDnq3$XG$s/"]},"shadow":false,"topLevel":false},"o":{"opcode":"control_if_else","next":null,"parent":"n","inputs":{"CONDITION":[2,"b)"],"SUBSTACK":[2,"a7"],"SUBSTACK2":[2,"a8"]},"fields":{},"shadow":false,"topLevel":false},"b)":{"opcode":"operator_equals","next":null,"parent":"o","inputs":{"OPERAND1":[3,[12,"MenuSelection","uzm+7ZecjQDnq3$XG$s/"],[10,""]],"OPERAND2":[1,[10,"1"]]},"fields":{},"shadow":false,"topLevel":false},"a7":{"opcode":"looks_setsizeto","next":null,"parent":"o","inputs":{"SIZE":[3,"a9",[4,"100"]]},"fields":{},"shadow":false,"topLevel":false},"a9":{"opcode":"operator_add","next":null,"parent":"a7","inputs":{"NUM1":[3,"b*",[4,""]],"NUM2":[1,[4,"100"]]},"fields":{},"shadow":false,"topLevel":false},"b*":{"opcode":"operator_multiply","next":null,"parent":"a9","inputs":{"NUM1":[3,[12,"CloneID2","*:$E$2ReHO~JTC;m1vW#"],[4,""]],"NUM2":[1,[4,"0.5"]]},"fields":{},"shadow":false,"topLevel":false},"a8":{"opcode":"looks_setsizeto","next":null,"parent":"o","inputs":{"SIZE":[3,"a!",[4,"100"]]},"fields":{},"shadow":false,"topLevel":false},"a!":{"opcode":"operator_add","next":null,"parent":"a8","inputs":{"NUM1":[3,"b+",[4,""]],"NUM2":[1,[4,"95"]]},"fields":{},"shadow":false,"topLevel":false},"b+":{"opcode":"operator_multiply","next":null,"parent":"a!","inputs":{"NUM1":[3,[12,"CloneID2","*:$E$2ReHO~JTC;m1vW#"],[4,""]],"NUM2":[1,[4,"0.5"]]},"fields":{},"shadow":false,"topLevel":false},"m":{"opcode":"control_if","next":"5","parent":"g","inputs":{"CONDITION":[2,"b,"],"SUBSTACK":[2,"a#"]},"fields":{},"shadow":false,"topLevel":false},"b,":{"opcode":"operator_equals","next":null,"parent":"m","inputs":{"OPERAND1":[3,[12,"CloneID","bohJIsLhCpZ;)4pO(kE`"],[10,""]],"OPERAND2":[1,[10,"2"]]},"fields":{},"shadow":false,"topLevel":false},"a#":{"opcode":"looks_seteffectto","next":"6","parent":"m","inputs":{"VALUE":[1,[4,"100"]]},"fields":{"EFFECT":["GHOST",null]},"shadow":false,"topLevel":false},"b-":{"opcode":"looks_costume","next":null,"parent":"6","inputs":{},"fields":{"COSTUME":["act1",null]},"shadow":true,"topLevel":false},"a%":{"opcode":"looks_gotofrontback","next":"C","parent":"6","inputs":{},"fields":{"FRONT_BACK":["front",null]},"shadow":false,"topLevel":false},"C":{"opcode":"looks_setsizeto","next":"B","parent":"a%","inputs":{"SIZE":[3,"a(",[4,"100"]]},"fields":{},"shadow":false,"topLevel":false},"a(":{"opcode":"operator_add","next":null,"parent":"C","inputs":{"NUM1":[3,"b.",[4,""]],"NUM2":[1,[4,"68.5"]]},"fields":{},"shadow":false,"topLevel":false},"b.":{"opcode":"operator_multiply","next":null,"parent":"a(","inputs":{"NUM1":[3,[12,"CloneID2","*:$E$2ReHO~JTC;m1vW#"],[4,""]],"NUM2":[1,[4,"0.5"]]},"fields":{},"shadow":false,"topLevel":false},"^":{"opcode":"operator_add","next":null,"parent":"B","inputs":{"NUM1":[1,[4,"-20"]],"NUM2":[3,"b/",[4,""]]},"fields":{},"shadow":false,"topLevel":false},"b/":{"opcode":"operator_multiply","next":null,"parent":"^","inputs":{"NUM1":[3,[12,"CloneID2","*:$E$2ReHO~JTC;m1vW#"],[4,""]],"NUM2":[1,[4,"2"]]},"fields":{},"shadow":false,"topLevel":false},"]":{"opcode":"motion_gotoxy","next":"D","parent":"B","inputs":{"X":[1,[4,"0"]],"Y":[1,[4,"-120"]]},"fields":{},"shadow":false,"topLevel":false},"bf":{"opcode":"operator_equals","next":null,"parent":"D","inputs":{"OPERAND1":[3,[12,"Menu Flag","=Wa={HPYEQm,6/~oB^h9"],[10,""]],"OPERAND2":[1,[10,"1"]]},"fields":{},"shadow":false,"topLevel":false},"bg":{"opcode":"looks_changeeffectby","next":null,"parent":"E","inputs":{"CHANGE":[1,[4,"-10"]]},"fields":{"EFFECT":["GHOST",null]},"shadow":false,"topLevel":false},"_":{"opcode":"control_forever","next":null,"parent":"E","inputs":{"SUBSTACK":[2,"q"]},"fields":{},"shadow":false,"topLevel":false},"q":{"opcode":"looks_switchcostumeto","next":"r","parent":"_","inputs":{"COSTUME":[3,"b:","b;"]},"fields":{},"shadow":false,"topLevel":false},"b:":{"opcode":"operator_join","next":null,"parent":"q","inputs":{"STRING1":[1,[10,"act"]],"STRING2":[3,[12,"act-temp","NA]Z`_G?%Xj5$R6a*vk^"],[10,"banana"]]},"fields":{},"shadow":false,"topLevel":false},"b;":{"opcode":"looks_costume","next":null,"parent":"q","inputs":{},"fields":{"COSTUME":["act6",null]},"shadow":true,"topLevel":false},"r":{"opcode":"control_if","next":"s","parent":"q","inputs":{"CONDITION":[2,"b="],"SUBSTACK":[2,"t"]},"fields":{},"shadow":false,"topLevel":false},"b=":{"opcode":"operator_equals","next":null,"parent":"r","inputs":{"OPERAND1":[3,[12,"CloneID2","*:$E$2ReHO~JTC;m1vW#"],[10,""]],"OPERAND2":[1,[10,"1"]]},"fields":{},"shadow":false,"topLevel":false},"t":{"opcode":"control_if_else","next":null,"parent":"r","inputs":{"CONDITION":[2,"a)"],"SUBSTACK":[2,"b?"],"SUBSTACK2":[2,"b@"]},"fields":{},"shadow":false,"topLevel":false},"a)":{"opcode":"sensing_touchingobject","next":null,"parent":"t","inputs":{"TOUCHINGOBJECTMENU":[1,"b["]},"fields":{},"shadow":false,"topLevel":false},"b[":{"opcode":"sensing_touchingobjectmenu","next":null,"parent":"a)","inputs":{},"fields":{"TOUCHINGOBJECTMENU":["_mouse_",null]},"shadow":true,"topLevel":false},"b?":{"opcode":"data_setvariableto","next":null,"parent":"t","inputs":{"VALUE":[1,[10,"2"]]},"fields":{"VARIABLE":["MenuSelection","uzm+7ZecjQDnq3$XG$s/"]},"shadow":false,"topLevel":false},"b@":{"opcode":"data_setvariableto","next":null,"parent":"t","inputs":{"VALUE":[1,[10,"0"]]},"fields":{"VARIABLE":["MenuSelection","uzm+7ZecjQDnq3$XG$s/"]},"shadow":false,"topLevel":false},"s":{"opcode":"control_if_else","next":null,"parent":"r","inputs":{"CONDITION":[2,"b]"],"SUBSTACK":[2,"7"],"SUBSTACK2":[2,"a*"]},"fields":{},"shadow":false,"topLevel":false},"b]":{"opcode":"operator_equals","next":null,"parent":"s","inputs":{"OPERAND1":[3,[12,"MenuSelection","uzm+7ZecjQDnq3$XG$s/"],[10,""]],"OPERAND2":[1,[10,"2"]]},"fields":{},"shadow":false,"topLevel":false},"a+":{"opcode":"operator_add","next":null,"parent":"7","inputs":{"NUM1":[3,"b^",[4,""]],"NUM2":[1,[4,"73.5"]]},"fields":{},"shadow":false,"topLevel":false},"b^":{"opcode":"operator_multiply","next":null,"parent":"a+","inputs":{"NUM1":[3,[12,"CloneID2","*:$E$2ReHO~JTC;m1vW#"],[4,""]],"NUM2":[1,[4,"0.5"]]},"fields":{},"shadow":false,"topLevel":false},"b_":{"opcode":"sensing_mousedown","next":null,"parent":"8","inputs":{},"fields":{},"shadow":false,"topLevel":false},"G":{"opcode":"control_if","next":null,"parent":"8","inputs":{"CONDITION":[2,"b`"],"SUBSTACK":[2,"F"]},"fields":{},"shadow":false,"topLevel":false},"b`":{"opcode":"operator_equals","next":null,"parent":"G","inputs":{"OPERAND1":[3,[12,"CloneID2","*:$E$2ReHO~JTC;m1vW#"],[10,""]],"OPERAND2":[1,[10,"1"]]},"fields":{},"shadow":false,"topLevel":false},"bh":{"opcode":"sound_sounds_menu","next":null,"parent":"F","inputs":{},"fields":{"SOUND_MENU":["mixkit-arcade-game-jump-coin-216",null]},"shadow":true,"topLevel":false},"a":{"opcode":"control_if_else","next":"H","parent":"F","inputs":{"CONDITION":[2,"b{"],"SUBSTACK":[2,"b|"],"SUBSTACK2":[2,"u"]},"fields":{},"shadow":false,"topLevel":false},"b{":{"opcode":"operator_equals","next":null,"parent":"a","inputs":{"OPERAND1":[3,[12,"act-temp","NA]Z`_G?%Xj5$R6a*vk^"],[10,""]],"OPERAND2":[1,[10,"3"]]},"fields":{},"shadow":false,"topLevel":false},"b|":{"opcode":"data_changevariableby","next":null,"parent":"a","inputs":{"VALUE":[1,[4,"0.5"]]},"fields":{"VARIABLE":["act-temp","NA]Z`_G?%Xj5$R6a*vk^"]},"shadow":false,"topLevel":false},"u":{"opcode":"control_if_else","next":null,"parent":"a","inputs":{"CONDITION":[2,"b}"],"SUBSTACK":[2,"b~"],"SUBSTACK2":[2,"ca"]},"fields":{},"shadow":false,"topLevel":false},"b}":{"opcode":"operator_equals","next":null,"parent":"u","inputs":{"OPERAND1":[3,[12,"act-temp","NA]Z`_G?%Xj5$R6a*vk^"],[10,""]],"OPERAND2":[1,[10,"3.5"]]},"fields":{},"shadow":false,"topLevel":false},"b~":{"opcode":"data_changevariableby","next":null,"parent":"u","inputs":{"VALUE":[1,[4,"0.5"]]},"fields":{"VARIABLE":["act-temp","NA]Z`_G?%Xj5$R6a*vk^"]},"shadow":false,"topLevel":false},"ca":{"opcode":"data_changevariableby","next":null,"parent":"u","inputs":{"VALUE":[1,[4,"1"]]},"fields":{"VARIABLE":["act-temp","NA]Z`_G?%Xj5$R6a*vk^"]},"shadow":false,"topLevel":false},"bi":{"opcode":"operator_gt","next":null,"parent":"H","inputs":{"OPERAND1":[3,[12,"act-temp","NA]Z`_G?%Xj5$R6a*vk^"],[10,""]],"OPERAND2":[3,[12,"☁ InfAct",";#50Qx=y]f!eqK|]bDP,"],[10,"50"]]},"fields":{},"shadow":false,"topLevel":false},"bj":{"opcode":"data_setvariableto","next":null,"parent":"H","inputs":{"VALUE":[1,[10,"1"]]},"fields":{"VARIABLE":["act-temp","NA]Z`_G?%Xj5$R6a*vk^"]},"shadow":false,"topLevel":false},"a*":{"opcode":"looks_setsizeto","next":null,"parent":"s","inputs":{"SIZE":[3,"a,",[4,"100"]]},"fields":{},"shadow":false,"topLevel":false},"a,":{"opcode":"operator_add","next":null,"parent":"a*","inputs":{"NUM1":[3,"cb",[4,""]],"NUM2":[1,[4,"68.5"]]},"fields":{},"shadow":false,"topLevel":false},"cb":{"opcode":"operator_multiply","next":null,"parent":"a,","inputs":{"NUM1":[3,[12,"CloneID2","*:$E$2ReHO~JTC;m1vW#"],[4,""]],"NUM2":[1,[4,"0.5"]]},"fields":{},"shadow":false,"topLevel":false},"cc":{"opcode":"operator_equals","next":null,"parent":"5","inputs":{"OPERAND1":[3,[12,"CloneID","bohJIsLhCpZ;)4pO(kE`"],[10,""]],"OPERAND2":[1,[10,"3"]]},"fields":{},"shadow":false,"topLevel":false},"a-":{"opcode":"looks_seteffectto","next":"9","parent":"5","inputs":{"VALUE":[1,[4,"100"]]},"fields":{"EFFECT":["GHOST",null]},"shadow":false,"topLevel":false},"cd":{"opcode":"looks_costume","next":null,"parent":"9","inputs":{},"fields":{"COSTUME":["Tutorial",null]},"shadow":true,"topLevel":false},"a.":{"opcode":"looks_gotofrontback","next":"!","parent":"9","inputs":{},"fields":{"FRONT_BACK":["front",null]},"shadow":false,"topLevel":false},"!":{"opcode":"looks_setsizeto","next":"#","parent":"a.","inputs":{"SIZE":[3,"a/",[4,"100"]]},"fields":{},"shadow":false,"topLevel":false},"a/":{"opcode":"operator_add","next":null,"parent":"!","inputs":{"NUM1":[3,"ce",[4,""]],"NUM2":[1,[4,"95"]]},"fields":{},"shadow":false,"topLevel":false},"ce":{"opcode":"operator_multiply","next":null,"parent":"a/","inputs":{"NUM1":[3,[12,"CloneID2","*:$E$2ReHO~JTC;m1vW#"],[4,""]],"NUM2":[1,[4,"0.5"]]},"fields":{},"shadow":false,"topLevel":false},"#":{"opcode":"looks_seteffectto","next":"%","parent":"!","inputs":{"VALUE":[3,"a:",[4,"0"]]},"fields":{"EFFECT":["BRIGHTNESS",null]},"shadow":false,"topLevel":false},"a:":{"opcode":"operator_add","next":null,"parent":"#","inputs":{"NUM1":[1,[4,"-20"]],"NUM2":[3,"cf",[4,""]]},"fields":{},"shadow":false,"topLevel":false},"cf":{"opcode":"operator_multiply","next":null,"parent":"a:","inputs":{"NUM1":[3,[12,"CloneID2","*:$E$2ReHO~JTC;m1vW#"],[4,""]],"NUM2":[1,[4,"2"]]},"fields":{},"shadow":false,"topLevel":false},"%":{"opcode":"control_wait_until","next":"a;","parent":"#","inputs":{"CONDITION":[2,"cg"]},"fields":{},"shadow":false,"topLevel":false},"cg":{"opcode":"operator_equals","next":null,"parent":"%","inputs":{"OPERAND1":[3,[12,"Menu Flag","=Wa={HPYEQm,6/~oB^h9"],[10,""]],"OPERAND2":[1,[10,"1"]]},"fields":{},"shadow":false,"topLevel":false},"a;":{"opcode":"motion_gotoxy","next":"(","parent":"%","inputs":{"X":[1,[4,"100"]],"Y":[1,[4,"-50"]]},"fields":{},"shadow":false,"topLevel":false},"(":{"opcode":"control_repeat","next":"a=","parent":"a;","inputs":{"TIMES":[1,[6,"10"]],"SUBSTACK":[2,"ch"]},"fields":{},"shadow":false,"topLevel":false},"ch":{"opcode":"looks_changeeffectby","next":null,"parent":"(","inputs":{"CHANGE":[1,[4,"-10"]]},"fields":{"EFFECT":["GHOST",null]},"shadow":false,"topLevel":false},"a=":{"opcode":"control_forever","next":null,"parent":"(","inputs":{"SUBSTACK":[2,"v"]},"fields":{},"shadow":false,"topLevel":false},"v":{"opcode":"control_if","next":"w","parent":"a=","inputs":{"CONDITION":[2,"ci"],"SUBSTACK":[2,"x"]},"fields":{},"shadow":false,"topLevel":false},"ci":{"opcode":"operator_equals","next":null,"parent":"v","inputs":{"OPERAND1":[3,[12,"CloneID2","*:$E$2ReHO~JTC;m1vW#"],[10,""]],"OPERAND2":[1,[10,"1"]]},"fields":{},"shadow":false,"topLevel":false},"x":{"opcode":"control_if_else","next":null,"parent":"v","inputs":{"CONDITION":[2,"a?"],"SUBSTACK":[2,"a@"],"SUBSTACK2":[2,"cj"]},"fields":{},"shadow":false,"topLevel":false},"a?":{"opcode":"sensing_touchingobject","next":null,"parent":"x","inputs":{"TOUCHINGOBJECTMENU":[1,"ck"]},"fields":{},"shadow":false,"topLevel":false},"ck":{"opcode":"sensing_touchingobjectmenu","next":null,"parent":"a?","inputs":{},"fields":{"TOUCHINGOBJECTMENU":["_mouse_",null]},"shadow":true,"topLevel":false},"a@":{"opcode":"data_setvariableto","next":")","parent":"x","inputs":{"VALUE":[1,[10,"3"]]},"fields":{"VARIABLE":["MenuSelection","uzm+7ZecjQDnq3$XG$s/"]},"shadow":false,"topLevel":false},")":{"opcode":"control_if","next":null,"parent":"a@","inputs":{"CONDITION":[2,"cl"],"SUBSTACK":[2,"*"]},"fields":{},"shadow":false,"topLevel":false},"cl":{"opcode":"sensing_mousedown","next":null,"parent":")","inputs":{},"fields":{},"shadow":false,"topLevel":false},"*":{"opcode":"control_repeat","next":"+","parent":")","inputs":{"TIMES":[1,[6,"10"]],"SUBSTACK":[2,"cm"]},"fields":{},"shadow":false,"topLevel":false},"cm":{"opcode":"looks_changeeffectby","next":null,"parent":"*","inputs":{"CHANGE":[1,[4,"10"]]},"fields":{"EFFECT":["GHOST",null]},"shadow":false,"topLevel":false},"+":{"opcode":"sound_play","next":"a[","parent":"*","inputs":{"SOUND_MENU":[1,"cn"]},"fields":{},"shadow":false,"topLevel":false},"cn":{"opcode":"sound_sounds_menu","next":null,"parent":"+","inputs":{},"fields":{"SOUND_MENU":["mixkit-arcade-game-jump-coin-216",null]},"shadow":true,"topLevel":false},"co":{"opcode":"event_broadcastandwait","next":null,"parent":"a[","inputs":{"BROADCAST_INPUT":[1,[11,"Darken","X|pIX.xai(-z?A#=}e,4"]]},"fields":{},"shadow":false,"topLevel":false},"cj":{"opcode":"data_setvariableto","next":null,"parent":"x","inputs":{"VALUE":[1,[10,"0"]]},"fields":{"VARIABLE":["MenuSelection","uzm+7ZecjQDnq3$XG$s/"]},"shadow":false,"topLevel":false},"w":{"opcode":"control_if_else","next":null,"parent":"v","inputs":{"CONDITION":[2,"cp"],"SUBSTACK":[2,"a]"],"SUBSTACK2":[2,"a^"]},"fields":{},"shadow":false,"topLevel":false},"cp":{"opcode":"operator_equals","next":null,"parent":"w","inputs":{"OPERAND1":[3,[12,"MenuSelection","uzm+7ZecjQDnq3$XG$s/"],[10,""]],"OPERAND2":[1,[10,"3"]]},"fields":{},"shadow":false,"topLevel":false},"a]":{"opcode":"looks_setsizeto","next":null,"parent":"w","inputs":{"SIZE":[3,"a_",[4,"100"]]},"fields":{},"shadow":false,"topLevel":false},"a_":{"opcode":"operator_add","next":null,"parent":"a]","inputs":{"NUM1":[3,"cq",[4,""]],"NUM2":[1,[4,"100"]]},"fields":{},"shadow":false,"topLevel":false},"cq":{"opcode":"operator_multiply","next":null,"parent":"a_","inputs":{"NUM1":[3,[12,"CloneID2","*:$E$2ReHO~JTC;m1vW#"],[4,""]],"NUM2":[1,[4,"0.5"]]},"fields":{},"shadow":false,"topLevel":false},"a^":{"opcode":"looks_setsizeto","next":null,"parent":"w","inputs":{"SIZE":[3,"a`",[4,"100"]]},"fields":{},"shadow":false,"topLevel":false},"a`":{"opcode":"operator_add","next":null,"parent":"a^","inputs":{"NUM1":[3,"cr",[4,""]],"NUM2":[1,[4,"95"]]},"fields":{},"shadow":false,"topLevel":false},"cr":{"opcode":"operator_multiply","next":null,"parent":"a`","inputs":{"NUM1":[3,[12,"CloneID2","*:$E$2ReHO~JTC;m1vW#"],[4,""]],"NUM2":[1,[4,"0.5"]]},"fields":{},"shadow":false,"topLevel":false},"a[":{"opcode":"data_setvariableto","next":"co","parent":"+","inputs":{"VALUE":[1,[10,"0"]]},"fields":{"VARIABLE":["act-temp","NA]Z`_G?%Xj5$R6a*vk^"]},"shadow":false,"topLevel":false},"at":{"opcode":"data_setvariableto","next":"aA","parent":"e","inputs":{"VALUE":[1,[10,"3"]]},"fields":{"VARIABLE":["CloneID","bohJIsLhCpZ;)4pO(kE`"]},"shadow":false,"topLevel":false},"aA":{"opcode":"data_setvariableto","next":"az","parent":"at","inputs":{"VALUE":[1,[10,"0"]]},"fields":{"VARIABLE":["CloneID2","*:$E$2ReHO~JTC;m1vW#"]},"shadow":false,"topLevel":false}},"comments":{},"currentCostume":1,"costumes":[{"assetId":"e5e4f7cd81d2d06e4625ccdf18f05033","name":"Caution","bitmapResolution":1,"md5ext":"e5e4f7cd81d2d06e4625ccdf18f05033.svg","dataFormat":"svg","rotationCenterX":335,"rotationCenterY":193.5},{"assetId":"60f53180916d7542df89ef59a7153e20","name":"BG","bitmapResolution":1,"md5ext":"60f53180916d7542df89ef59a7153e20.svg","dataFormat":"svg","rotationCenterX":335.5,"rotationCenterY":193},{"assetId":"ea49e6307e127ab45e7c6d96a536807a","name":"Title","bitmapResolution":1,"md5ext":"ea49e6307e127ab45e7c6d96a536807a.svg","dataFormat":"svg","rotationCenterX":207.18466955579646,"rotationCenterY":134.81431666666668},{"assetId":"66c8d6d887620fe84833bc4ed97b1a58","name":"costume1","bitmapResolution":1,"md5ext":"66c8d6d887620fe84833bc4ed97b1a58.svg","dataFormat":"svg","rotationCenterX":84.625,"rotationCenterY":46.940277777777766},{"assetId":"ca9888c8fa8919d9e922311b07e6c785","name":"act1","bitmapResolution":1,"md5ext":"ca9888c8fa8919d9e922311b07e6c785.svg","dataFormat":"svg","rotationCenterX":115.12500000000006,"rotationCenterY":27.44028000000003},{"assetId":"6f36f4165a30ff87d3c419cc6d4ba551","name":"act2","bitmapResolution":1,"md5ext":"6f36f4165a30ff87d3c419cc6d4ba551.svg","dataFormat":"svg","rotationCenterX":115.12500000000006,"rotationCenterY":27.44028000000003},{"assetId":"0e14a59ca51d1776e685aacf5b186e97","name":"act3","bitmapResolution":1,"md5ext":"0e14a59ca51d1776e685aacf5b186e97.svg","dataFormat":"svg","rotationCenterX":115.12500000000006,"rotationCenterY":27.44028000000003},{"assetId":"7ab2031fe27138418d2569bfad3cc9b3","name":"act3.5","bitmapResolution":1,"md5ext":"7ab2031fe27138418d2569bfad3cc9b3.svg","dataFormat":"svg","rotationCenterX":115.12500000000006,"rotationCenterY":27.44028000000003},{"assetId":"81e0e005f71cf4b9a8905558601204cc","name":"act4","bitmapResolution":1,"md5ext":"81e0e005f71cf4b9a8905558601204cc.svg","dataFormat":"svg","rotationCenterX":115.12500000000006,"rotationCenterY":27.44028000000003},{"assetId":"a4e7a239c4a3c4593c0c9eed8db70e42","name":"act5","bitmapResolution":1,"md5ext":"a4e7a239c4a3c4593c0c9eed8db70e42.svg","dataFormat":"svg","rotationCenterX":115.12500000000006,"rotationCenterY":27.44028000000003},{"assetId":"c3a700e35fdd84464cfe582f37b426dc","name":"act6","bitmapResolution":1,"md5ext":"c3a700e35fdd84464cfe582f37b426dc.svg","dataFormat":"svg","rotationCenterX":115.12500000000006,"rotationCenterY":27.44028000000003},{"assetId":"b5e2d0ab2fd579eac70ae40e5a5782e0","name":"act7","bitmapResolution":1,"md5ext":"b5e2d0ab2fd579eac70ae40e5a5782e0.svg","dataFormat":"svg","rotationCenterX":115.12500000000006,"rotationCenterY":29.104944605809152},{"assetId":"e1727fa4161c8ad7709e312965b54a6f","name":"Tutorial","bitmapResolution":1,"md5ext":"e1727fa4161c8ad7709e312965b54a6f.svg","dataFormat":"svg","rotationCenterX":84.625,"rotationCenterY":46.940277777777766}],"sounds":[{"assetId":"2c405a25ff2a9c46712886b69435cb4f","name":"mixkit-arcade-game-jump-coin-216","dataFormat":"wav","rate":48000,"sampleCount":5999,"md5ext":"2c405a25ff2a9c46712886b69435cb4f.wav"}],"volume":100,"layerOrder":1,"visible":true,"x":0,"y":0,"size":100,"direction":90,"draggable":false,"rotationStyle":"all around"}],"monitors":[{"id":"undefined_direction","mode":"default","opcode":"motion_direction","params":{},"spriteName":"Actual Player shown because Scratch has a stupid glitch that physically moves the player up and down while changing costumes and sensing at the same time in the same script.  Ugh, someone please fix that.","value":0,"width":0,"height":0,"x":215,"y":50,"visible":false,"sliderMin":0,"sliderMax":100,"isDiscrete":true},{"id":"undefined_costumenumbername_number","mode":"default","opcode":"looks_costumenumbername","params":{"NUMBER_NAME":"number"},"spriteName":"Actual Player shown because Scratch has a stupid glitch that physically moves the player up and down while changing costumes and sensing at the same time in the same script.  Ugh, someone please fix that.","value":0,"width":0,"height":0,"x":-80,"y":246,"visible":false,"sliderMin":0,"sliderMax":100,"isDiscrete":true},{"id":":}LB~=1grhGm7IUX)EDw-Player Start Y-list","mode":"list","opcode":"data_listcontents","params":{"LIST":"Player Start Y"},"spriteName":null,"value":0,"width":272,"height":372,"x":-75,"y":59,"visible":false},{"id":":}LB~=1grhGm7IUX)EDw-Player Start X-list","mode":"list","opcode":"data_listcontents","params":{"LIST":"Player Start X"},"spriteName":null,"value":0,"width":272,"height":372,"x":-75,"y":266,"visible":false},{"id":":}LB~=1grhGm7IUX)EDw-Projectile Y-list","mode":"list","opcode":"data_listcontents","params":{"LIST":"Projectile Y"},"spriteName":null,"value":0,"width":270,"height":370,"x":34,"y":302,"visible":false},{"id":":}LB~=1grhGm7IUX)EDw-Projectile X-list","mode":"list","opcode":"data_listcontents","params":{"LIST":"Projectile X"},"spriteName":null,"value":0,"width":270,"height":370,"x":22,"y":254,"visible":false},{"id":":}LB~=1grhGm7IUX)EDw-Projectile lifespan-list","mode":"list","opcode":"data_listcontents","params":{"LIST":"Projectile lifespan"},"spriteName":null,"value":0,"width":271,"height":366,"x":252,"y":5,"visible":false},{"id":":}LB~=1grhGm7IUX)EDw-Only bad to enemies?-list","mode":"list","opcode":"data_listcontents","params":{"LIST":"Only bad to enemies?"},"spriteName":null,"value":0,"width":291,"height":366,"x":252,"y":212,"visible":false},{"id":":}LB~=1grhGm7IUX)EDw-Projectile Xv-list","mode":"list","opcode":"data_listcontents","params":{"LIST":"Projectile Xv"},"spriteName":null,"value":0,"width":266,"height":366,"x":16,"y":17,"visible":false},{"id":":}LB~=1grhGm7IUX)EDw-Projectile Yv-list","mode":"list","opcode":"data_listcontents","params":{"LIST":"Projectile Yv"},"spriteName":null,"value":0,"width":266,"height":366,"x":290,"y":315,"visible":false},{"id":":}LB~=1grhGm7IUX)EDw-Projectile type-list","mode":"list","opcode":"data_listcontents","params":{"LIST":"Projectile type"},"spriteName":null,"value":0,"width":266,"height":366,"x":-3,"y":173,"visible":false},{"id":":}LB~=1grhGm7IUX)EDw-Direction-list","mode":"list","opcode":"data_listcontents","params":{"LIST":"Direction"},"spriteName":null,"value":0,"width":266,"height":366,"x":147,"y":128,"visible":false},{"id":":}LB~=1grhGm7IUX)EDw-Costume #-list","mode":"list","opcode":"data_listcontents","params":{"LIST":"Costume #"},"spriteName":null,"value":0,"width":264,"height":364,"x":312,"y":234,"visible":false},{"id":":}LB~=1grhGm7IUX)EDw-Size-list","mode":"list","opcode":"data_listcontents","params":{"LIST":"Size"},"spriteName":null,"value":0,"width":264,"height":364,"x":290,"y":136,"visible":false},{"id":":}LB~=1grhGm7IUX)EDw-Size (for hurting)-list","mode":"list","opcode":"data_listcontents","params":{"LIST":"Size (for hurting)"},"spriteName":null,"value":0,"width":244,"height":344,"x":179,"y":147,"visible":false},{"id":"bohJIsLhCpZ;)4pO(kE`","mode":"default","opcode":"data_variable","params":{"VARIABLE":"CloneID"},"spriteName":"Main Menu","value":0,"width":0,"height":0,"x":-75,"y":5,"visible":false,"sliderMin":0,"sliderMax":100,"isDiscrete":true},{"id":"*:$E$2ReHO~JTC;m1vW#","mode":"default","opcode":"data_variable","params":{"VARIABLE":"CloneID2"},"spriteName":"Main Menu","value":0,"width":0,"height":0,"x":-75,"y":5,"visible":false,"sliderMin":0,"sliderMax":100,"isDiscrete":true},{"id":"=Wa={HPYEQm,6/~oB^h9","mode":"default","opcode":"data_variable","params":{"VARIABLE":"Menu Flag"},"spriteName":null,"value":0,"width":0,"height":0,"x":-75,"y":5,"visible":false,"sliderMin":0,"sliderMax":100,"isDiscrete":true},{"id":"uzm+7ZecjQDnq3$XG$s/","mode":"default","opcode":"data_variable","params":{"VARIABLE":"MenuSelection"},"spriteName":null,"value":0,"width":0,"height":0,"x":-75,"y":32,"visible":false,"sliderMin":0,"sliderMax":100,"isDiscrete":true},{"id":".v#L4N66Rb^[IHcNI2@K","mode":"default","opcode":"data_variable","params":{"VARIABLE":"☁ InfDone"},"spriteName":null,"value":0,"width":0,"height":0,"x":-75,"y":32,"visible":false,"sliderMin":0,"sliderMax":100,"isDiscrete":true},{"id":"MU2C1L@}Q}(^Efc:)C$H","mode":"default","opcode":"data_variable","params":{"VARIABLE":"☁ redirect"},"spriteName":null,"value":0,"width":0,"height":0,"x":-75,"y":32,"visible":false,"sliderMin":0,"sliderMax":100,"isDiscrete":true},{"id":"p%U,g:cj-*ZR61(^4]B}","mode":"default","opcode":"data_variable","params":{"VARIABLE":"temp"},"spriteName":null,"value":0,"width":0,"height":0,"x":-75,"y":5,"visible":false,"sliderMin":0,"sliderMax":100,"isDiscrete":true},{"id":"sensing_username","mode":"default","opcode":"sensing_username","params":{},"spriteName":null,"value":0,"width":0,"height":0,"x":-75,"y":86,"visible":false,"sliderMin":0,"sliderMax":100,"isDiscrete":true},{"id":"ZzkoA%G]o9|X9o-)W$i$","mode":"default","opcode":"data_variable","params":{"VARIABLE":"☁ InfHP"},"spriteName":null,"value":0,"width":0,"height":0,"x":-75,"y":5,"visible":false,"sliderMin":0,"sliderMax":100,"isDiscrete":true},{"id":"H$^*.cx%vxB9[$Qbs=Ty","mode":"default","opcode":"data_variable","params":{"VARIABLE":"☁ InfWeaponsUnlocked"},"spriteName":null,"value":0,"width":0,"height":0,"x":-75,"y":5,"visible":false,"sliderMin":0,"sliderMax":100,"isDiscrete":true},{"id":";#50Qx=y]f!eqK|]bDP,","mode":"default","opcode":"data_variable","params":{"VARIABLE":"☁ InfAct"},"spriteName":null,"value":0,"width":0,"height":0,"x":-75,"y":5,"visible":false,"sliderMin":0,"sliderMax":100,"isDiscrete":true},{"id":"NA]Z`_G?%Xj5$R6a*vk^","mode":"default","opcode":"data_variable","params":{"VARIABLE":"act-temp"},"spriteName":null,"value":0,"width":0,"height":0,"x":-80,"y":5,"visible":false,"sliderMin":0,"sliderMax":100,"isDiscrete":true}],"extensions":[],"meta":{"semver":"3.0.0","vm":"0.2.0","agent":""}}